keyring_otp-0.2.dist-info/DESCRIPTION.rst
keyring_otp-0.2.dist-info/METADATA
keyring_otp-0.2.dist-info/RECORD
keyring_otp-0.2.dist-info/WHEEL
keyring_otp-0.2.dist-info/entry_points.txt
keyring_otp-0.2.dist-info/metadata.json
keyring_otp-0.2.dist-info/top_level.txt
kotp/__init__.py
kotp/cli.py
kotp/kotp.py
kotp/tests/__init__.py
kotp/tests/test_kotp.py
