Metadata-Version: 2.0
Name: keyring-otp
Version: 0.2
Summary: OTP command line tool
Home-page: https://github.com/petrus-v/keyring-otp
Author: Pierre Verkest
Author-email: pverkest@anybox.fr
License: GPLv3
Keywords: keyring otp totp
Platform: UNKNOWN
Classifier: Development Status :: 4 - Beta
Classifier: Environment :: Console
Classifier: Intended Audience :: Developers
Classifier: Intended Audience :: System Administrators
Classifier: License :: OSI Approved :: GNU Lesser General Public License v3 or later (LGPLv3+)
Classifier: Programming Language :: Python :: 3
Classifier: Topic :: Utilities
Requires-Dist: pyotp
Requires-Dist: xerox
Requires-Dist: secretstorage
